flask_pubsub.py
setup.py
Flask_PubSub.egg-info/PKG-INFO
Flask_PubSub.egg-info/SOURCES.txt
Flask_PubSub.egg-info/dependency_links.txt
Flask_PubSub.egg-info/requires.txt
Flask_PubSub.egg-info/top_level.txt