Metadata-Version: 1.0
Name: Flask-PubSub
Version: 0.1.0
Summary: Flask-PubSub
Home-page: https://github.com/raicheff/flask-pubsub
Author: Boris Raicheff
Author-email: b@raicheff.com
License: UNKNOWN
Platform: UNKNOWN
